stockstats_polars/__init__.py
stockstats_polars/polars_namespace.py
stockstats_polars-0.1.0.dist-info/licenses/LICENSE-MIT
stockstats_polars-0.1.0.dist-info/METADATA
stockstats_polars-0.1.0.dist-info/WHEEL
stockstats_polars-0.1.0.dist-info/top_level.txt
stockstats_polars-0.1.0.dist-info/RECORD
